status_checker.py
pystatuschecker-0.1.3.dist-info/DESCRIPTION.rst
pystatuschecker-0.1.3.dist-info/METADATA
pystatuschecker-0.1.3.dist-info/RECORD
pystatuschecker-0.1.3.dist-info/WHEEL
pystatuschecker-0.1.3.dist-info/metadata.json
pystatuschecker-0.1.3.dist-info/top_level.txt
